xpmir_rust-0.21.0.dist-info/METADATA
xpmir_rust-0.21.0.dist-info/WHEEL
xpmir_rust-0.21.0.dist-info/license_files/LICENSE.txt
xpmir_rust/__init__.py
xpmir_rust/xpmir_rust.abi3.so
xpmir_rust-0.21.0.dist-info/RECORD
