Metadata-Version: 2.1
Name: xpmir-rust
Version: 0.21.0
Classifier: Programming Language :: Rust
Classifier: Programming Language :: Python :: Implementation :: CPython
Classifier: Programming Language :: Python :: Implementation :: PyPy
License-File: LICENSE.txt
Author: Benjamin Piwowarski <benjamin@piwowarski.fr>
Author-email: Benjamin Piwowarski <benjamin@piwowarski.fr>
License: GPL-2.0-or-later
Requires-Python: >=3.8
